{"chunk_definitions":[{"row":26,"row_count":1,"visible":true,"expansion_state":0,"options":{"engine":"r","echo":true,"include":true,"label":"unnamed-chunk-75","dev":"png"},"document_id":"8DD89A56","chunk_id":"c8bric9li1b8k","chunk_label":"unnamed-chunk-1"},{"row":44,"row_count":1,"visible":true,"expansion_state":0,"options":{"engine":"r","echo":false,"fig.width":12,"fig.height":9,"label":"unnamed-chunk-1","dev":"png"},"document_id":"B9AC6060","chunk_id":"c1pltpts06xyp","chunk_label":"unnamed-chunk-2"},{"row":64,"row_count":1,"visible":true,"expansion_state":0,"options":{"engine":"r","echo":false,"fig.width":12,"fig.height":9,"label":"unnamed-chunk-77","dev":"png"},"document_id":"B9AC6060","chunk_id":"cq2stq0mh9hvs","chunk_label":"unnamed-chunk-3"},{"row":82,"row_count":1,"visible":true,"expansion_state":0,"options":{"engine":"r","echo":false,"fig.width":12,"fig.height":9,"label":"unnamed-chunk-78","dev":"png"},"document_id":"B9AC6060","chunk_id":"cj5q98mqdlz4o","chunk_label":"unnamed-chunk-4"},{"row":104,"row_count":1,"visible":true,"expansion_state":0,"options":{"engine":"r","echo":false,"include":false,"label":"unnamed-chunk-79","dev":"png"},"document_id":"B9AC6060","chunk_id":"c65227g8txeag","chunk_label":"unnamed-chunk-5"},{"row":120,"row_count":1,"visible":true,"expansion_state":0,"options":{"engine":"r","echo":false,"fig.width":12,"fig.height":9,"label":"unnamed-chunk-80","dev":"png"},"document_id":"B9AC6060","chunk_id":"c8nbdpxa13z7h","chunk_label":"unnamed-chunk-6"},{"row":133,"row_count":1,"visible":true,"expansion_state":0,"options":{"engine":"r","echo":false,"include":false,"label":"unnamed-chunk-81","dev":"png"},"document_id":"B9AC6060","chunk_id":"cmqdnx8dgg1da","chunk_label":"unnamed-chunk-7"},{"row":149,"row_count":1,"visible":true,"expansion_state":0,"options":{"engine":"r","echo":false,"fig.width":12,"fig.height":9,"label":"unnamed-chunk-82","dev":"png"},"document_id":"B9AC6060","chunk_id":"csbao4xh5ddsz","chunk_label":"unnamed-chunk-8"},{"row":185,"row_count":1,"visible":true,"expansion_state":0,"options":{"engine":"r","echo":false,"include":false,"label":"unnamed-chunk-83","dev":"png"},"document_id":"B9AC6060","chunk_id":"c85wkfzgnt5ci","chunk_label":"unnamed-chunk-9"},{"row":201,"row_count":1,"visible":true,"expansion_state":0,"options":{"engine":"r","echo":false,"fig.width":12,"fig.height":9,"label":"unnamed-chunk-84","dev":"png"},"document_id":"B9AC6060","chunk_id":"cwrm5n3m5p6pj","chunk_label":"unnamed-chunk-10"},{"row":211,"row_count":1,"visible":true,"expansion_state":0,"options":{"engine":"r","echo":false,"include":false,"label":"unnamed-chunk-85","dev":"png"},"document_id":"B9AC6060","chunk_id":"cvblexvkucik5","chunk_label":"unnamed-chunk-11"},{"row":227,"row_count":1,"visible":true,"expansion_state":0,"options":{"engine":"r","echo":false,"fig.width":12,"fig.height":9,"label":"unnamed-chunk-86","dev":"png"},"document_id":"B9AC6060","chunk_id":"cok2zdvgpzdt0","chunk_label":"unnamed-chunk-12"},{"row":238,"row_count":1,"visible":true,"expansion_state":0,"options":{"engine":"r","echo":false,"include":false,"label":"unnamed-chunk-87","dev":"png"},"document_id":"B9AC6060","chunk_id":"cinkmad0kd0mj","chunk_label":"unnamed-chunk-13"},{"row":254,"row_count":1,"visible":true,"expansion_state":0,"options":{"engine":"r","echo":false,"fig.width":12,"fig.height":9,"label":"unnamed-chunk-88","dev":"png"},"document_id":"B9AC6060","chunk_id":"c37q8hxtke54m","chunk_label":"unnamed-chunk-14"}],"doc_write_time":1735246974}